Workbook

Sheet Portfolio Overview
A1: GPP2026 GROUP 4 — PORTFOLIO OVERVIEW & KEY STATS (ex-CAT)
A3: SIMULATION SUMMARY
A4: Starting Value | B4: $100,000,000 | C4: Portfolio Return (total) | D4: =(B22-100000000)/100000000 -> 0.0291011
A5: Starting Date | B5: 28 Jun 2026 | C5: Best Week | D5: 7/31 → 8/7 (+$2.8M)
A6: End Date | B6: 11 Sep 2026 | C6: Worst Week | D6: 7/10 → 7/17 (-$2.7M)
A7: Benchmark | B7: 60/40 MSCI/Global Agg | C7: Top Contributor | D7: ='Attribution Analysis'!K24 -> MSFT (35.77%)
A8: Team Role | B8: Macro/Fixed Income Analyst | C8: Largest Detractor | D8: ='Attribution Analysis'!K26 -> WMT (-11.32%)
A9: Current Value | B9: =B22 -> 102910110 | C9: Fixed Income Sleeve | D9: 26.5% portfolio
A11: WEEKLY PORTFOLIO VALUE & RETURN
A12: Friday | B12: Portfolio Value ($) | C12: Weekly Return | D12: Cumulative Return
A13: 6/26/2026 | B13: ='CAT Removal Log'!D14 -> 1.0044591e+08 | C13: =(B13-100000000)/100000000 -> 0.0044590773 | D13: =(B13-100000000)/100000000 -> 0.0044590773
A14: 7/3/2026 | B14: ='CAT Removal Log'!D15 -> 1.0073642e+08 | C14: =(B14-B13)/B13 -> 0.0028921792 | D14: =(B14-100000000)/100000000 -> 0.007364153
A15: 7/10/2026 | B15: ='CAT Removal Log'!D16 -> 100771209 | C15: =(B15-B14)/B14 -> 0.00034539347 | D15: =(B15-100000000)/100000000 -> 0.00771209
A16: 7/17/2026 | B16: ='CAT Removal Log'!D17 -> 98090805 | C16: =(B16-B15)/B15 -> -0.02659891 | D16: =(B16-100000000)/100000000 -> -0.019091953
A17: 7/24/2026 | B17: ='CAT Removal Log'!D18 -> 98978520 | C17: =(B17-B16)/B16 -> 0.0090499343 | D17: =(B17-100000000)/100000000 -> -0.0102148
A18: 7/31/2026 | B18: ='CAT Removal Log'!D19 -> 100923640 | C18: =(B18-B17)/B17 -> 0.019651941 | D18: =(B18-100000000)/100000000 -> 0.0092364
A19: 8/7/2026 | B19: ='CAT Removal Log'!D20 -> 103697680 | C19: =(B19-B18)/B18 -> 0.027486523 | D19: =(B19-100000000)/100000000 -> 0.0369768
A20: 8/14/2026 | B20: ='CAT Removal Log'!D21 -> 105174120 | C20: =(B20-B19)/B19 -> 0.014237927 | D20: =(B20-100000000)/100000000 -> 0.0517412
A21: 8/21/2026 | B21: ='CAT Removal Log'!D22 -> 103154120 | C21: =(B21-B20)/B20 -> -0.019206246 | D21: =(B21-100000000)/100000000 -> 0.0315412
A22: 8/28/2026 | B22: ='CAT Removal Log'!D23 -> 102910110 | C22: =(B22-B21)/B21 -> -0.0023654896 | D22: =(B22-100000000)/100000000 -> 0.0291011

Sheet Position PL Tracker
A1: POSITION-LEVEL P/L TRACKER — ALL 10 FRIDAYS (Real StockTrak Data, ex-CAT)
A2: Ticker | B2: Asset Class | C2: Weight | D2: 6/26/2026 | F2: 7/3/2026 | H2: 7/10/2026 | J2: 7/17/2026 | L2: 7/24/2026 | N2: 7/31/2026 | P2: 8/7/2026 | R2: 8/14/2026 | T2: 8/21/2026 | V2: 8/28/2026
D3: P/L ($) | E3: P/L % | F3: P/L ($) | G3: P/L % | H3: P/L ($) | I3: P/L % | J3: P/L ($) | K3: P/L % | L3: P/L ($) | M3: P/L % | N3: P/L ($) | O3: P/L % | P3: P/L ($) | Q3: P/L % | R3: P/L ($) | S3: P/L % | T3: P/L ($) | U3: P/L % | V3: P/L ($) | W3: P/L %
A4: AAPL | B4: Equity | C4: 0.05 | D4: — | E4: — | F4: -33451.89 | G4: -0.0066 | H4: 287777.75 | I4: 0.0566 | J4: 829114.84 | K4: 0.1633 | L4: 1031909.2 | M4: 0.2032 | N4: 1081941 | O4: 0.2131 | P4: 717351.42 | Q4: 0.1413 | R4: 789513.56 | S4: 0.1556 | T4: 672484.88 | U4: 0.1324 | V4: 580592.8 | W4: 0.1143
A5: MSFT | B5: Equity | C5: 0.06 | D5: — | E5: — | F5: 198133.86 | G5: 0.0324 | H5: 598999.47 | I5: 0.098 | J5: 251949.99 | K5: 0.0412 | L5: 978699.99 | M5: 0.16 | N5: 1192819.3 | O5: 0.1955 | P5: 1844163.5 | Q5: 0.3021 | R5: 1985726.3 | S5: 0.3252 | T5: 2106266.5 | U5: 0.3449 | V5: 2186583.3 | W5: 0.3577
A6: MU | B6: Equity | C6: 0.1 | D6: 95699.1 | E6: 0.0383 | F6: -738024.2 | G6: -0.0685 | H6: -1771207.8 | I6: -0.1644 | J6: -2040841.1 | K6: -0.1894 | L6: -1491898.3 | M6: -0.1384 | N6: -1182667.4 | O6: -0.1097 | P6: -910668.7 | Q6: -0.0845 | R6: -813147.4 | S6: -0.0755 | T6: -1050226.3 | U6: -0.0973 | V6: -1177407.2 | W6: -0.1093
A7: DAL | B7: Equity | C7: 0.015 | D7: 105435.9 | E7: 0.0702 | F7: -10593.3 | G7: -0.0071 | H7: -80770.5 | I7: -0.0538 | J7: -40472.1 | K7: -0.0269 | L7: -56123.1 | M7: -0.0373 | N7: -89976.6 | O7: -0.0599 | P7: -130389.3 | Q7: -0.0868 | R7: -114992.4 | S7: -0.0766 | T7: -110844.6 | U7: -0.0738 | V7: -111689.1 | W7: -0.0743
A8: WMT | B8: Equity | C8: 0.04 | D8: — | E8: — | F8: -662665.6 | G8: -0.1643 | H8: -624053.6 | I8: -0.1547 | J8: -69626.4 | K8: -0.0173 | L8: -58561.6 | M8: -0.0145 | N8: -243253.4 | O8: -0.0604 | P8: -456739.2 | Q8: -0.1134 | R8: -385543.2 | S8: -0.0957 | T8: -412828.8 | U8: -0.1025 | V8: -455862.4 | W8: -0.1132
A9: IAG | B9: Equity | C9: 0.005 | D9: 11298 | E9: 0.0299 | F9: -10491 | G9: -0.0277 | H9: -21789 | I9: -0.0576 | J9: -33636.36 | K9: -0.0661 | L9: -21789 | M9: -0.0576 | N9: -19368 | O9: -0.0512 | P9: -25824 | Q9: -0.0683 | R9: -22596 | S9: -0.0597 | T9: -24210 | U9: -0.064 | V9: -33311.17 | W9: -0.0651
A10: SPY | B10: Equity ETF | C10: 0.14 | D10: -148967.84 | E10: -0.0106 | F10: 80754.25 | G10: 0.0058 | H10: 90064.74 | I10: 0.0064 | J10: 122746.46 | K10: 0.0088 | L10: 420881.16 | M10: 0.0301 | N10: 486438.43 | O10: 0.0347 | P10: 481708.34 | Q10: 0.0344 | R10: 598781.33 | S10: 0.0428 | T10: 366637.12 | U10: 0.0262 | V10: 617912.52 | W10: 0.0441
A11: VT | B11: Equity ETF | C11: 0.1 | D11: — | E11: — | F11: 36064 | G11: 0.0036 | H11: 58616 | I11: 0.0059 | J11: -12236 | K11: -0.0012 | L11: 216628 | M11: 0.0217 | N11: 257680 | O11: 0.0258 | P11: 337880 | Q11: 0.0338 | R11: 444360 | S11: 0.0445 | T11: 345828 | U11: 0.0346 | V11: 388976 | W11: 0.039
A12: SPCX | B12: Equity ETF | C12: 0.03 | D12: — | E12: — | F12: -701478.96 | G12: -0.227 | H12: -713432.04 | I12: -0.2308 | J12: -652584.24 | K12: -0.2111 | L12: -564873.96 | M12: -0.1827 | N12: -591299.08 | O12: -0.1913 | P12: -474880.44 | Q12: -0.1536 | R12: -387889.64 | S12: -0.1255 | T12: -353023.96 | U12: -0.1142 | V12: -308197.56 | W12: -0.0997
A13: EEM | B13: Equity ETF | C13: 0.03 | D13: — | E13: — | F13: -56832 | G13: -0.0191 | H13: -167388 | I13: -0.0563 | J13: -163836 | K13: -0.0551 | L13: -136836 | M13: -0.046 | N13: -124764 | O13: -0.0419 | P13: -78144 | Q13: -0.0263 | R13: -24420 | S13: -0.0082 | T13: -124764 | U13: -0.0419 | V13: -163836 | W13: -0.0551
A14: XLV | B14: Sector ETF | C14: 0.06 | D14: — | E14: — | F14: 154643.99 | G14: 0.0254 | H14: 169393.28 | I14: 0.0279 | J14: 6049.76 | K14: 0.001 | L14: 94945.61 | M14: 0.0156 | N14: 190945.55 | O14: 0.0314 | P14: 314587.52 | Q14: 0.0517 | R14: 363837.82 | S14: 0.0598 | T14: 338346.18 | U14: 0.0556 | V14: 386806.53 | W14: 0.0636
A15: XLF | B15: Sector ETF | C15: 0.05 | D15: — | E15: — | F15: 176013.12 | G15: 0.035 | H15: 345472.56 | I15: 0.0687 | J15: 235931.28 | K15: 0.0469 | L15: 294909.6 | M15: 0.0586 | N15: 352977.48 | O15: 0.0701 | P15: 403522.44 | Q15: 0.0802 | R15: 418369.08 | S15: 0.0831 | T15: 352977.48 | U15: 0.0701 | V15: 408200.64 | W15: 0.0811
A16: VGIT | B16: Fixed Income | C16: 0.1 | D16: — | E16: — | F16: -42460 | G16: -0.0042 | H16: -49253.6 | I16: -0.0049 | J16: -83221.6 | K16: -0.0083 | L16: -57745.6 | M16: -0.0057 | N16: -66237.6 | O16: -0.0066 | P16: -91713.6 | Q16: -0.0091 | R16: -112094.4 | S16: -0.0112 | T16: -123982 | U16: -0.0123 | V16: -157951.2 | W16: -0.0157
A17: VTIP | B17: Fixed Income | C17: 0.06 | D17: — | E17: — | F17: -36057 | G17: -0.006 | H17: -43268.4 | I17: -0.0072 | J17: -68508.3 | K17: -0.0113 | L17: -46874.1 | M17: -0.0078 | N17: -42066.5 | O17: -0.007 | P17: -58893.1 | Q17: -0.0098 | R17: -66104.5 | S17: -0.011 | T17: -70912.1 | U17: -0.0118 | V17: -74517.8 | W17: -0.0123
A18: JPIE | B18: Fixed Income | C18: 0.06 | D18: — | E18: — | F18: 6551.5 | G18: 0.0011 | H18: -1310.3 | I18: -0.0002 | J18: -23585.4 | K18: -0.0039 | L18: -3930.9 | M18: -0.0007 | N18: -9172.1 | O18: -0.0015 | P18: -19654.5 | Q18: -0.0033 | R18: -28826.6 | S18: -0.0048 | T18: -37998.7 | U18: -0.0063 | V18: -35378.1 | W18: -0.0059
A19: MINT | B19: Fixed Income | C19: 0.045 | D19: — | E19: — | F19: 1794.6 | G19: 0.0004 | H19: 2691.9 | I19: 0.0006 | J19: -6281.1 | K19: -0.0014 | L19: -3140.55 | M19: -0.0007 | N19: -1345.95 | O19: -0.0003 | P19: 448.65 | Q19: 0.0001 | R19: 897.3 | S19: 0.0002 | T19: 897.3 | U19: 0.0002 | V19: 0 | W19: 0
A20: TOTAL | C20: =SUM(C4:C19) -> 0.945 | D20: =SUM(D4:D19) -> 63465.16 | E20: =SUMPRODUCT($C$4:$C$19,E4:E19) -> 0.0035485 | F20: =SUM(F4:F19) -> -1638098.6 | G20: =SUMPRODUCT($C$4:$C$19,G4:G19) -> -0.015686 | H20: =SUM(H4:H19) -> -1919457.5 | I20: =SUMPRODUCT($C$4:$C$19,I4:I19) -> -0.017938 | J20: =SUM(J4:J19) -> -1749036.3 | K20: =SUMPRODUCT($C$4:$C$19,K4:K19) -> -0.016003 | L20: =SUM(L4:L19) -> 596200.47 | M20: =SUMPRODUCT($C$4:$C$19,M4:M19) -> 0.00677 | N20: =SUM(N4:N19) -> 1192651.1 | O20: =SUMPRODUCT($C$4:$C$19,O4:O19) -> 0.012492 | P20: =SUM(P4:P19) -> 1852755 | Q20: =SUMPRODUCT($C$4:$C$19,Q4:Q19) -> 0.018781 | R20: =SUM(R4:R19) -> 2645871.3 | S20: =SUMPRODUCT($C$4:$C$19,S4:S19) -> 0.0265815 | T20: =SUM(T4:T19) -> 1874647 | U20: =SUMPRODUCT($C$4:$C$19,U4:U19) -> 0.019036 | V20: =SUM(V4:V19) -> 2050921.3 | W20: =SUMPRODUCT($C$4:$C$19,W4:W19) -> 0.020918

Sheet Attribution Analysis
A1: RETURN ATTRIBUTION — CONTRIBUTION IN BASIS POINTS (bps) — ex-CAT
A2: Ticker / Metric | B2: 6/26 | C2: 7/3 | D2: 7/10 | E2: 7/17 | F2: 7/24 | G2: 7/31 | H2: 8/7 | I2: 8/14 | J2: 8/21 | K2: 8/28
A3: AAPL | B3: =IF(ISNUMBER('Position PL Tracker'!E4),'Position PL Tracker'!$C4*'Position PL Tracker'!E4*10000,"—") -> — | C3: =IF(ISNUMBER('Position PL Tracker'!G4),'Position PL Tracker'!$C4*'Position PL Tracker'!G4*10000,"—") -> -3.3 | D3: =IF(ISNUMBER('Position PL Tracker'!I4),'Position PL Tracker'!$C4*'Position PL Tracker'!I4*10000,"—") -> 28.3 | E3: =IF(ISNUMBER('Position PL Tracker'!K4),'Position PL Tracker'!$C4*'Position PL Tracker'!K4*10000,"—") -> 81.65 | F3: =IF(ISNUMBER('Position PL Tracker'!M4),'Position PL Tracker'!$C4*'Position PL Tracker'!M4*10000,"—") -> 101.6 | G3: =IF(ISNUMBER('Position PL Tracker'!O4),'Position PL Tracker'!$C4*'Position PL Tracker'!O4*10000,"—") -> 106.55 | H3: =IF(ISNUMBER('Position PL Tracker'!Q4),'Position PL Tracker'!$C4*'Position PL Tracker'!Q4*10000,"—") -> 70.65 | I3: =IF(ISNUMBER('Position PL Tracker'!S4),'Position PL Tracker'!$C4*'Position PL Tracker'!S4*10000,"—") -> 77.8 | J3: =IF(ISNUMBER('Position PL Tracker'!U4),'Position PL Tracker'!$C4*'Position PL Tracker'!U4*10000,"—") -> 66.2 | K3: =IF(ISNUMBER('Position PL Tracker'!W4),'Position PL Tracker'!$C4*'Position PL Tracker'!W4*10000,"—") -> 57.15
A4: MSFT | B4: =IF(ISNUMBER('Position PL Tracker'!E5),'Position PL Tracker'!$C5*'Position PL Tracker'!E5*10000,"—") -> — | C4: =IF(ISNUMBER('Position PL Tracker'!G5),'Position PL Tracker'!$C5*'Position PL Tracker'!G5*10000,"—") -> 19.44 | D4: =IF(ISNUMBER('Position PL Tracker'!I5),'Position PL Tracker'!$C5*'Position PL Tracker'!I5*10000,"—") -> 58.8 | E4: =IF(ISNUMBER('Position PL Tracker'!K5),'Position PL Tracker'!$C5*'Position PL Tracker'!K5*10000,"—") -> 24.72 | F4: =IF(ISNUMBER('Position PL Tracker'!M5),'Position PL Tracker'!$C5*'Position PL Tracker'!M5*10000,"—") -> 96 | G4: =IF(ISNUMBER('Position PL Tracker'!O5),'Position PL Tracker'!$C5*'Position PL Tracker'!O5*10000,"—") -> 117.3 | H4: =IF(ISNUMBER('Position PL Tracker'!Q5),'Position PL Tracker'!$C5*'Position PL Tracker'!Q5*10000,"—") -> 181.26 | I4: =IF(ISNUMBER('Position PL Tracker'!S5),'Position PL Tracker'!$C5*'Position PL Tracker'!S5*10000,"—") -> 195.12 | J4: =IF(ISNUMBER('Position PL Tracker'!U5),'Position PL Tracker'!$C5*'Position PL Tracker'!U5*10000,"—") -> 206.94 | K4: =IF(ISNUMBER('Position PL Tracker'!W5),'Position PL Tracker'!$C5*'Position PL Tracker'!W5*10000,"—") -> 214.62
A5: MU | B5: =IF(ISNUMBER('Position PL Tracker'!E6),'Position PL Tracker'!$C6*'Position PL Tracker'!E6*10000,"—") -> 38.3 | C5: =IF(ISNUMBER('Position PL Tracker'!G6),'Position PL Tracker'!$C6*'Position PL Tracker'!G6*10000,"—") -> -68.5 | D5: =IF(ISNUMBER('Position PL Tracker'!I6),'Position PL Tracker'!$C6*'Position PL Tracker'!I6*10000,"—") -> -164.4 | E5: =IF(ISNUMBER('Position PL Tracker'!K6),'Position PL Tracker'!$C6*'Position PL Tracker'!K6*10000,"—") -> -189.4 | F5: =IF(ISNUMBER('Position PL Tracker'!M6),'Position PL Tracker'!$C6*'Position PL Tracker'!M6*10000,"—") -> -138.4 | G5: =IF(ISNUMBER('Position PL Tracker'!O6),'Position PL Tracker'!$C6*'Position PL Tracker'!O6*10000,"—") -> -109.7 | H5: =IF(ISNUMBER('Position PL Tracker'!Q6),'Position PL Tracker'!$C6*'Position PL Tracker'!Q6*10000,"—") -> -84.5 | I5: =IF(ISNUMBER('Position PL Tracker'!S6),'Position PL Tracker'!$C6*'Position PL Tracker'!S6*10000,"—") -> -75.5 | J5: =IF(ISNUMBER('Position PL Tracker'!U6),'Position PL Tracker'!$C6*'Position PL Tracker'!U6*10000,"—") -> -97.3 | K5: =IF(ISNUMBER('Position PL Tracker'!W6),'Position PL Tracker'!$C6*'Position PL Tracker'!W6*10000,"—") -> -109.3
A6: DAL | B6: =IF(ISNUMBER('Position PL Tracker'!E7),'Position PL Tracker'!$C7*'Position PL Tracker'!E7*10000,"—") -> 10.53 | C6: =IF(ISNUMBER('Position PL Tracker'!G7),'Position PL Tracker'!$C7*'Position PL Tracker'!G7*10000,"—") -> -1.065 | D6: =IF(ISNUMBER('Position PL Tracker'!I7),'Position PL Tracker'!$C7*'Position PL Tracker'!I7*10000,"—") -> -8.07 | E6: =IF(ISNUMBER('Position PL Tracker'!K7),'Position PL Tracker'!$C7*'Position PL Tracker'!K7*10000,"—") -> -4.035 | F6: =IF(ISNUMBER('Position PL Tracker'!M7),'Position PL Tracker'!$C7*'Position PL Tracker'!M7*10000,"—") -> -5.595 | G6: =IF(ISNUMBER('Position PL Tracker'!O7),'Position PL Tracker'!$C7*'Position PL Tracker'!O7*10000,"—") -> -8.985 | H6: =IF(ISNUMBER('Position PL Tracker'!Q7),'Position PL Tracker'!$C7*'Position PL Tracker'!Q7*10000,"—") -> -13.02 | I6: =IF(ISNUMBER('Position PL Tracker'!S7),'Position PL Tracker'!$C7*'Position PL Tracker'!S7*10000,"—") -> -11.49 | J6: =IF(ISNUMBER('Position PL Tracker'!U7),'Position PL Tracker'!$C7*'Position PL Tracker'!U7*10000,"—") -> -11.07 | K6: =IF(ISNUMBER('Position PL Tracker'!W7),'Position PL Tracker'!$C7*'Position PL Tracker'!W7*10000,"—") -> -11.145
A7: WMT | B7: =IF(ISNUMBER('Position PL Tracker'!E8),'Position PL Tracker'!$C8*'Position PL Tracker'!E8*10000,"—") -> — | C7: =IF(ISNUMBER('Position PL Tracker'!G8),'Position PL Tracker'!$C8*'Position PL Tracker'!G8*10000,"—") -> -65.72 | D7: =IF(ISNUMBER('Position PL Tracker'!I8),'Position PL Tracker'!$C8*'Position PL Tracker'!I8*10000,"—") -> -61.88 | E7: =IF(ISNUMBER('Position PL Tracker'!K8),'Position PL Tracker'!$C8*'Position PL Tracker'!K8*10000,"—") -> -6.92 | F7: =IF(ISNUMBER('Position PL Tracker'!M8),'Position PL Tracker'!$C8*'Position PL Tracker'!M8*10000,"—") -> -5.8 | G7: =IF(ISNUMBER('Position PL Tracker'!O8),'Position PL Tracker'!$C8*'Position PL Tracker'!O8*10000,"—") -> -24.16 | H7: =IF(ISNUMBER('Position PL Tracker'!Q8),'Position PL Tracker'!$C8*'Position PL Tracker'!Q8*10000,"—") -> -45.36 | I7: =IF(ISNUMBER('Position PL Tracker'!S8),'Position PL Tracker'!$C8*'Position PL Tracker'!S8*10000,"—") -> -38.28 | J7: =IF(ISNUMBER('Position PL Tracker'!U8),'Position PL Tracker'!$C8*'Position PL Tracker'!U8*10000,"—") -> -41 | K7: =IF(ISNUMBER('Position PL Tracker'!W8),'Position PL Tracker'!$C8*'Position PL Tracker'!W8*10000,"—") -> -45.28
A8: IAG | B8: =IF(ISNUMBER('Position PL Tracker'!E9),'Position PL Tracker'!$C9*'Position PL Tracker'!E9*10000,"—") -> 1.495 | C8: =IF(ISNUMBER('Position PL Tracker'!G9),'Position PL Tracker'!$C9*'Position PL Tracker'!G9*10000,"—") -> -1.385 | D8: =IF(ISNUMBER('Position PL Tracker'!I9),'Position PL Tracker'!$C9*'Position PL Tracker'!I9*10000,"—") -> -2.88 | E8: =IF(ISNUMBER('Position PL Tracker'!K9),'Position PL Tracker'!$C9*'Position PL Tracker'!K9*10000,"—") -> -3.305 | F8: =IF(ISNUMBER('Position PL Tracker'!M9),'Position PL Tracker'!$C9*'Position PL Tracker'!M9*10000,"—") -> -2.88 | G8: =IF(ISNUMBER('Position PL Tracker'!O9),'Position PL Tracker'!$C9*'Position PL Tracker'!O9*10000,"—") -> -2.56 | H8: =IF(ISNUMBER('Position PL Tracker'!Q9),'Position PL Tracker'!$C9*'Position PL Tracker'!Q9*10000,"—") -> -3.415 | I8: =IF(ISNUMBER('Position PL Tracker'!S9),'Position PL Tracker'!$C9*'Position PL Tracker'!S9*10000,"—") -> -2.985 | J8: =IF(ISNUMBER('Position PL Tracker'!U9),'Position PL Tracker'!$C9*'Position PL Tracker'!U9*10000,"—") -> -3.2 | K8: =IF(ISNUMBER('Position PL Tracker'!W9),'Position PL Tracker'!$C9*'Position PL Tracker'!W9*10000,"—") -> -3.255
A9: SPY | B9: =IF(ISNUMBER('Position PL Tracker'!E10),'Position PL Tracker'!$C10*'Position PL Tracker'!E10*10000,"—") -> -14.84 | C9: =IF(ISNUMBER('Position PL Tracker'!G10),'Position PL Tracker'!$C10*'Position PL Tracker'!G10*10000,"—") -> 8.12 | D9: =IF(ISNUMBER('Position PL Tracker'!I10),'Position PL Tracker'!$C10*'Position PL Tracker'!I10*10000,"—") -> 8.96 | E9: =IF(ISNUMBER('Position PL Tracker'!K10),'Position PL Tracker'!$C10*'Position PL Tracker'!K10*10000,"—") -> 12.32 | F9: =IF(ISNUMBER('Position PL Tracker'!M10),'Position PL Tracker'!$C10*'Position PL Tracker'!M10*10000,"—") -> 42.14 | G9: =IF(ISNUMBER('Position PL Tracker'!O10),'Position PL Tracker'!$C10*'Position PL Tracker'!O10*10000,"—") -> 48.58 | H9: =IF(ISNUMBER('Position PL Tracker'!Q10),'Position PL Tracker'!$C10*'Position PL Tracker'!Q10*10000,"—") -> 48.16 | I9: =IF(ISNUMBER('Position PL Tracker'!S10),'Position PL Tracker'!$C10*'Position PL Tracker'!S10*10000,"—") -> 59.92 | J9: =IF(ISNUMBER('Position PL Tracker'!U10),'Position PL Tracker'!$C10*'Position PL Tracker'!U10*10000,"—") -> 36.68 | K9: =IF(ISNUMBER('Position PL Tracker'!W10),'Position PL Tracker'!$C10*'Position PL Tracker'!W10*10000,"—") -> 61.74
A10: VT | B10: =IF(ISNUMBER('Position PL Tracker'!E11),'Position PL Tracker'!$C11*'Position PL Tracker'!E11*10000,"—") -> — | C10: =IF(ISNUMBER('Position PL Tracker'!G11),'Position PL Tracker'!$C11*'Position PL Tracker'!G11*10000,"—") -> 3.6 | D10: =IF(ISNUMBER('Position PL Tracker'!I11),'Position PL Tracker'!$C11*'Position PL Tracker'!I11*10000,"—") -> 5.9 | E10: =IF(ISNUMBER('Position PL Tracker'!K11),'Position PL Tracker'!$C11*'Position PL Tracker'!K11*10000,"—") -> -1.2 | F10: =IF(ISNUMBER('Position PL Tracker'!M11),'Position PL Tracker'!$C11*'Position PL Tracker'!M11*10000,"—") -> 21.7 | G10: =IF(ISNUMBER('Position PL Tracker'!O11),'Position PL Tracker'!$C11*'Position PL Tracker'!O11*10000,"—") -> 25.8 | H10: =IF(ISNUMBER('Position PL Tracker'!Q11),'Position PL Tracker'!$C11*'Position PL Tracker'!Q11*10000,"—") -> 33.8 | I10: =IF(ISNUMBER('Position PL Tracker'!S11),'Position PL Tracker'!$C11*'Position PL Tracker'!S11*10000,"—") -> 44.5 | J10: =IF(ISNUMBER('Position PL Tracker'!U11),'Position PL Tracker'!$C11*'Position PL Tracker'!U11*10000,"—") -> 34.6 | K10: =IF(ISNUMBER('Position PL Tracker'!W11),'Position PL Tracker'!$C11*'Position PL Tracker'!W11*10000,"—") -> 39
A11: SPCX | B11: =IF(ISNUMBER('Position PL Tracker'!E12),'Position PL Tracker'!$C12*'Position PL Tracker'!E12*10000,"—") -> — | C11: =IF(ISNUMBER('Position PL Tracker'!G12),'Position PL Tracker'!$C12*'Position PL Tracker'!G12*10000,"—") -> -68.1 | D11: =IF(ISNUMBER('Position PL Tracker'!I12),'Position PL Tracker'!$C12*'Position PL Tracker'!I12*10000,"—") -> -69.24 | E11: =IF(ISNUMBER('Position PL Tracker'!K12),'Position PL Tracker'!$C12*'Position PL Tracker'!K12*10000,"—") -> -63.33 | F11: =IF(ISNUMBER('Position PL Tracker'!M12),'Position PL Tracker'!$C12*'Position PL Tracker'!M12*10000,"—") -> -54.81 | G11: =IF(ISNUMBER('Position PL Tracker'!O12),'Position PL Tracker'!$C12*'Position PL Tracker'!O12*10000,"—") -> -57.39 | H11: =IF(ISNUMBER('Position PL Tracker'!Q12),'Position PL Tracker'!$C12*'Position PL Tracker'!Q12*10000,"—") -> -46.08 | I11: =IF(ISNUMBER('Position PL Tracker'!S12),'Position PL Tracker'!$C12*'Position PL Tracker'!S12*10000,"—") -> -37.65 | J11: =IF(ISNUMBER('Position PL Tracker'!U12),'Position PL Tracker'!$C12*'Position PL Tracker'!U12*10000,"—") -> -34.26 | K11: =IF(ISNUMBER('Position PL Tracker'!W12),'Position PL Tracker'!$C12*'Position PL Tracker'!W12*10000,"—") -> -29.91
A12: EEM | B12: =IF(ISNUMBER('Position PL Tracker'!E13),'Position PL Tracker'!$C13*'Position PL Tracker'!E13*10000,"—") -> — | C12: =IF(ISNUMBER('Position PL Tracker'!G13),'Position PL Tracker'!$C13*'Position PL Tracker'!G13*10000,"—") -> -5.73 | D12: =IF(ISNUMBER('Position PL Tracker'!I13),'Position PL Tracker'!$C13*'Position PL Tracker'!I13*10000,"—") -> -16.89 | E12: =IF(ISNUMBER('Position PL Tracker'!K13),'Position PL Tracker'!$C13*'Position PL Tracker'!K13*10000,"—") -> -16.53 | F12: =IF(ISNUMBER('Position PL Tracker'!M13),'Position PL Tracker'!$C13*'Position PL Tracker'!M13*10000,"—") -> -13.8 | G12: =IF(ISNUMBER('Position PL Tracker'!O13),'Position PL Tracker'!$C13*'Position PL Tracker'!O13*10000,"—") -> -12.57 | H12: =IF(ISNUMBER('Position PL Tracker'!Q13),'Position PL Tracker'!$C13*'Position PL Tracker'!Q13*10000,"—") -> -7.89 | I12: =IF(ISNUMBER('Position PL Tracker'!S13),'Position PL Tracker'!$C13*'Position PL Tracker'!S13*10000,"—") -> -2.46 | J12: =IF(ISNUMBER('Position PL Tracker'!U13),'Position PL Tracker'!$C13*'Position PL Tracker'!U13*10000,"—") -> -12.57 | K12: =IF(ISNUMBER('Position PL Tracker'!W13),'Position PL Tracker'!$C13*'Position PL Tracker'!W13*10000,"—") -> -16.53
A13: XLV | B13: =IF(ISNUMBER('Position PL Tracker'!E14),'Position PL Tracker'!$C14*'Position PL Tracker'!E14*10000,"—") -> — | C13: =IF(ISNUMBER('Position PL Tracker'!G14),'Position PL Tracker'!$C14*'Position PL Tracker'!G14*10000,"—") -> 15.24 | D13: =IF(ISNUMBER('Position PL Tracker'!I14),'Position PL Tracker'!$C14*'Position PL Tracker'!I14*10000,"—") -> 16.74 | E13: =IF(ISNUMBER('Position PL Tracker'!K14),'Position PL Tracker'!$C14*'Position PL Tracker'!K14*10000,"—") -> 0.6 | F13: =IF(ISNUMBER('Position PL Tracker'!M14),'Position PL Tracker'!$C14*'Position PL Tracker'!M14*10000,"—") -> 9.36 | G13: =IF(ISNUMBER('Position PL Tracker'!O14),'Position PL Tracker'!$C14*'Position PL Tracker'!O14*10000,"—") -> 18.84 | H13: =IF(ISNUMBER('Position PL Tracker'!Q14),'Position PL Tracker'!$C14*'Position PL Tracker'!Q14*10000,"—") -> 31.02 | I13: =IF(ISNUMBER('Position PL Tracker'!S14),'Position PL Tracker'!$C14*'Position PL Tracker'!S14*10000,"—") -> 35.88 | J13: =IF(ISNUMBER('Position PL Tracker'!U14),'Position PL Tracker'!$C14*'Position PL Tracker'!U14*10000,"—") -> 33.36 | K13: =IF(ISNUMBER('Position PL Tracker'!W14),'Position PL Tracker'!$C14*'Position PL Tracker'!W14*10000,"—") -> 38.16
A14: XLF | B14: =IF(ISNUMBER('Position PL Tracker'!E15),'Position PL Tracker'!$C15*'Position PL Tracker'!E15*10000,"—") -> — | C14: =IF(ISNUMBER('Position PL Tracker'!G15),'Position PL Tracker'!$C15*'Position PL Tracker'!G15*10000,"—") -> 17.5 | D14: =IF(ISNUMBER('Position PL Tracker'!I15),'Position PL Tracker'!$C15*'Position PL Tracker'!I15*10000,"—") -> 34.35 | E14: =IF(ISNUMBER('Position PL Tracker'!K15),'Position PL Tracker'!$C15*'Position PL Tracker'!K15*10000,"—") -> 23.45 | F14: =IF(ISNUMBER('Position PL Tracker'!M15),'Position PL Tracker'!$C15*'Position PL Tracker'!M15*10000,"—") -> 29.3 | G14: =IF(ISNUMBER('Position PL Tracker'!O15),'Position PL Tracker'!$C15*'Position PL Tracker'!O15*10000,"—") -> 35.05 | H14: =IF(ISNUMBER('Position PL Tracker'!Q15),'Position PL Tracker'!$C15*'Position PL Tracker'!Q15*10000,"—") -> 40.1 | I14: =IF(ISNUMBER('Position PL Tracker'!S15),'Position PL Tracker'!$C15*'Position PL Tracker'!S15*10000,"—") -> 41.55 | J14: =IF(ISNUMBER('Position PL Tracker'!U15),'Position PL Tracker'!$C15*'Position PL Tracker'!U15*10000,"—") -> 35.05 | K14: =IF(ISNUMBER('Position PL Tracker'!W15),'Position PL Tracker'!$C15*'Position PL Tracker'!W15*10000,"—") -> 40.55
... A18: MINT | B18: =IF(ISNUMBER('Position PL Tracker'!E19),'Position PL Tracker'!$C19*'Position PL Tracker'!E19*10000,"—") -> — | C18: =IF(ISNUMBER('Position PL Tracker'!G19),'Position PL Tracker'!$C19*'Position PL Tracker'!G19*10000,"—") -> 0.18 | D18: =IF(ISNUMBER('Position PL Tracker'!I19),'Position PL Tracker'!$C19*'Position PL Tracker'!I19*10000,"—") -> 0.27 | E18: =IF(ISNUMBER('Position PL Tracker'!K19),'Position PL Tracker'!$C19*'Position PL Tracker'!K19*10000,"—") -> -0.63 | F18: =IF(ISNUMBER('Position PL Tracker'!M19),'Position PL Tracker'!$C19*'Position PL Tracker'!M19*10000,"—") -> -0.315 | G18: =IF(ISNUMBER('Position PL Tracker'!O19),'Position PL Tracker'!$C19*'Position PL Tracker'!O19*10000,"—") -> -0.135 | H18: =IF(ISNUMBER('Position PL Tracker'!Q19),'Position PL Tracker'!$C19*'Position PL Tracker'!Q19*10000,"—") -> 0.045 | I18: =IF(ISNUMBER('Position PL Tracker'!S19),'Position PL Tracker'!$C19*'Position PL Tracker'!S19*10000,"—") -> 0.09 | J18: =IF(ISNUMBER('Position PL Tracker'!U19),'Position PL Tracker'!$C19*'Position PL Tracker'!U19*10000,"—") -> 0.09 | K18: =IF(ISNUMBER('Position PL Tracker'!W19),'Position PL Tracker'!$C19*'Position PL Tracker'!W19*10000,"—") -> 0
A21: EQUITY TOTAL | B21: =SUM(B3:B14) -> 35.485 | C21: =SUM(C3:C14) -> -149.9 | D21: =SUM(D3:D14) -> -170.31 | E21: =SUM(E3:E14) -> -141.98 | F21: =SUM(F3:F14) -> 78.815 | G21: =SUM(G3:G14) -> 136.755 | H21: =SUM(H3:H14) -> 204.725 | I21: =SUM(I3:I14) -> 286.405 | ... K21: =SUM(K3:K14) -> 235.8
A22: FIXED INCOME TOTAL | B22: =SUM(B15:B18) -> 0 | C22: =SUM(C15:C18) -> -6.96 | D22: =SUM(D15:D18) -> -9.07 | E22: =SUM(E15:E18) -> -18.05 | F22: =SUM(F15:F18) -> -11.115 | G22: =SUM(G15:G18) -> -11.835 | H22: =SUM(H15:H18) -> -16.915 | I22: =SUM(I15:I18) -> -20.59 | ... K22: =SUM(K15:K18) -> -26.62
A23: PORTFOLIO TOTAL | B23: =B21+B22 -> 35.485 | C23: =C21+C22 -> -156.86 | D23: =D21+D22 -> -179.38 | E23: =E21+E22 -> -160.03 | F23: =F21+F22 -> 67.7 | G23: =G21+G22 -> 124.92 | H23: =H21+H22 -> 187.81 | I23: =I21+I22 -> 265.815 | ... K23: =K21+K22 -> 209.18
A24: Best Contributor | B24: =INDEX('Position PL Tracker'!$A$4:$A$19,MATCH(MAX('Position PL Tracker'!E$4:E$19),'Position PL Tracker'!E$4:E$19,0))&" ("&TEXT(MAX('Position PL Tracker'!E$4:E$19),"0.00%")&")" -> DAL (7.02%) | C24: =INDEX('Position PL Tracker'!$A$4:$A$19,MATCH(MAX('Position PL Tracker'!G$4:G$19),'Position PL Tracker'!G$4:G$19,0))&" ("&TEXT(MAX('Position PL Tracker'!G$4:G$19),"0.00%")&")" -> XLF (3.50%) | D24: =INDEX('Position PL Tracker'!$A$4:$A$19,MATCH(MAX('Position PL Tracker'!I$4:I$19),'Position PL Tracker'!I$4:I$19,0))&" ("&TEXT(MAX('Position PL Tracker'!I$4:I$19),"0.00%")&")" -> MSFT (9.80%) | E24: =INDEX('Position PL Tracker'!$A$4:$A$19,MATCH(MAX('Position PL Tracker'!K$4:K$19),'Position PL Tracker'!K$4:K$19,0))&" ("&TEXT(MAX('Position PL Tracker'!K$4:K$19),"0.00%")&")" -> AAPL (16.33%) | F24: =INDEX('Position PL Tracker'!$A$4:$A$19,MATCH(MAX('Position PL Tracker'!M$4:M$19),'Position PL Tracker'!M$4:M$19,0))&" ("&TEXT(MAX('Position PL Tracker'!M$4:M$19),"0.00%")&")" -> AAPL (20.32%) | G24: =INDEX('Position PL Tracker'!$A$4:$A$19,MATCH(MAX('Position PL Tracker'!O$4:O$19),'Position PL Tracker'!O$4:O$19,0))&" ("&TEXT(MAX('Position PL Tracker'!O$4:O$19),"0.00%")&")" -> AAPL (21.31%) | H24: =INDEX('Position PL Tracker'!$A$4:$A$19,MATCH(MAX('Position PL Tracker'!Q$4:Q$19),'Position PL Tracker'!Q$4:Q$19,0))&" ("&TEXT(MAX('Position PL Tracker'!Q$4:Q$19),"0.00%")&")" -> MSFT (30.21%) | I24: =INDEX('Position PL Tracker'!$A$4:$A$19,MATCH(MAX('Position PL Tracker'!S$4:S$19),'Position PL Tracker'!S$4:S$19,0))&" ("&TEXT(MAX('Position PL Tracker'!S$4:S$19),"0.00%")&")" -> MSFT (32.52%) | J24: =INDEX('Position PL Tracker'!$A$4:$A$19,MATCH(MAX('Position PL Tracker'!U$4:U$19),'Position PL Tracker'!U$4:U$19,0))&" ("&TEXT(MAX('Position PL Tracker'!U$4:U$19),"0.00%")&")" -> MSFT (34.49%) | K24: =INDEX('Position PL Tracker'!$A$4:$A$19,MATCH(MAX('Position PL Tracker'!W$4:W$19),'Position PL Tracker'!W$4:W$19,0))&" ("&TEXT(MAX('Position PL Tracker'!W$4:W$19),"0.00%")&")" -> MSFT (35.77%)
A26: Worst Contributor | B26: =INDEX('Position PL Tracker'!$A$4:$A$19,MATCH(MIN('Position PL Tracker'!E$4:E$19),'Position PL Tracker'!E$4:E$19,0))&" ("&TEXT(MIN('Position PL Tracker'!E$4:E$19),"0.00%")&")" -> SPY (-1.06%) | C26: =INDEX('Position PL Tracker'!$A$4:$A$19,MATCH(MIN('Position PL Tracker'!G$4:G$19),'Position PL Tracker'!G$4:G$19,0))&" ("&TEXT(MIN('Position PL Tracker'!G$4:G$19),"0.00%")&")" -> SPCX (-22.70%) | D26: =INDEX('Position PL Tracker'!$A$4:$A$19,MATCH(MIN('Position PL Tracker'!I$4:I$19),'Position PL Tracker'!I$4:I$19,0))&" ("&TEXT(MIN('Position PL Tracker'!I$4:I$19),"0.00%")&")" -> SPCX (-23.08%) | E26: =INDEX('Position PL Tracker'!$A$4:$A$19,MATCH(MIN('Position PL Tracker'!K$4:K$19),'Position PL Tracker'!K$4:K$19,0))&" ("&TEXT(MIN('Position PL Tracker'!K$4:K$19),"0.00%")&")" -> SPCX (-21.11%) | F26: =INDEX('Position PL Tracker'!$A$4:$A$19,MATCH(MIN('Position PL Tracker'!M$4:M$19),'Position PL Tracker'!M$4:M$19,0))&" ("&TEXT(MIN('Position PL Tracker'!M$4:M$19),"0.00%")&")" -> SPCX (-18.27%) | G26: =INDEX('Position PL Tracker'!$A$4:$A$19,MATCH(MIN('Position PL Tracker'!O$4:O$19),'Position PL Tracker'!O$4:O$19,0))&" ("&TEXT(MIN('Position PL Tracker'!O$4:O$19),"0.00%")&")" -> SPCX (-19.13%) | H26: =INDEX('Position PL Tracker'!$A$4:$A$19,MATCH(MIN('Position PL Tracker'!Q$4:Q$19),'Position PL Tracker'!Q$4:Q$19,0))&" ("&TEXT(MIN('Position PL Tracker'!Q$4:Q$19),"0.00%")&")" -> SPCX (-15.36%) | I26: =INDEX('Position PL Tracker'!$A$4:$A$19,MATCH(MIN('Position PL Tracker'!S$4:S$19),'Position PL Tracker'!S$4:S$19,0))&" ("&TEXT(MIN('Position PL Tracker'!S$4:S$19),"0.00%")&")" -> SPCX (-12.55%) | J26: =INDEX('Position PL Tracker'!$A$4:$A$19,MATCH(MIN('Position PL Tracker'!U$4:U$19),'Position PL Tracker'!U$4:U$19,0))&" ("&TEXT(MIN('Position PL Tracker'!U$4:U$19),"0.00%")&")" -> SPCX (-11.42%) | K26: =INDEX('Position PL Tracker'!$A$4:$A$19,MATCH(MIN('Position PL Tracker'!W$4:W$19),'Position PL Tracker'!W$4:W$19,0))&" ("&TEXT(MIN('Position PL Tracker'!W$4:W$19),"0.00%")&")" -> WMT (-11.32%)

Sheet Weekly Performance
A1: WEEKLY PERFORMANCE vs BENCHMARK — SHARPE & INFORMATION RATIO
A3: FILL IN BENCHMARK RETURNS (col E) FROM YAHOO FINANCE EACH FRIDAY
A8: 📋 Formula: Benchmark = 0.60 × VT weekly return + 0.40 × VGIT weekly return | Copy from Tab 'Benchmark Calc'
A9: # | B9: Friday | C9: Portfolio Value ($) | D9: Portfolio Return | E9: Benchmark Return | F9: Active Return (bps) | G9: Cumulative Port Return | H9: Cumulative Bench Return
A10: 1 | B10: 6/26/2026 | C10: ='Portfolio Overview'!B13 -> 1.0044591e+08 | D10: =(C10-100000000)/100000000 -> 0.0044590773 | E10: [fill] | F10: =IFERROR((D10-E10)*10000,0) -> 0 | G10: =(C10-100000000)/100000000 -> 0.0044590773 | H10: =IFERROR(E10,0) -> [fill]
A11: 2 | B11: 7/3/2026 | C11: ='Portfolio Overview'!B14 -> 1.0073642e+08 | D11: =(C11-C10)/C10 -> 0.0028921792 | E11: [fill] | F11: =IFERROR((D11-E11)*10000,0) -> 0 | G11: =(C11-100000000)/100000000 -> 0.007364153 | H11: =IFERROR((1+H10)*(1+E11)-1,0) -> 0
A12: 3 | B12: 7/10/2026 | C12: ='Portfolio Overview'!B15 -> 100771209 | D12: =(C12-C11)/C11 -> 0.00034539347 | E12: [fill] | F12: =IFERROR((D12-E12)*10000,0) -> 0 | G12: =(C12-100000000)/100000000 -> 0.00771209 | H12: =IFERROR((1+H11)*(1+E12)-1,0) -> 0
A13: 4 | B13: 7/17/2026 | C13: ='Portfolio Overview'!B16 -> 98090805 | D13: =(C13-C12)/C12 -> -0.02659891 | E13: [fill] | F13: =IFERROR((D13-E13)*10000,0) -> 0 | G13: =(C13-100000000)/100000000 -> -0.019091953 | H13: =IFERROR((1+H12)*(1+E13)-1,0) -> 0
A14: 5 | B14: 7/24/2026 | C14: ='Portfolio Overview'!B17 -> 98978520 | D14: =(C14-C13)/C13 -> 0.0090499343 | E14: [fill] | F14: =IFERROR((D14-E14)*10000,0) -> 0 | G14: =(C14-100000000)/100000000 -> -0.0102148 | H14: =IFERROR((1+H13)*(1+E14)-1,0) -> 0
A15: 6 | B15: 7/31/2026 | C15: ='Portfolio Overview'!B18 -> 100923640 | D15: =(C15-C14)/C14 -> 0.019651941 | E15: [fill] | F15: =IFERROR((D15-E15)*10000,0) -> 0 | G15: =(C15-100000000)/100000000 -> 0.0092364 | H15: =IFERROR((1+H14)*(1+E15)-1,0) -> 0
A16: 7 | B16: 8/7/2026 | C16: ='Portfolio Overview'!B19 -> 103697680 | D16: =(C16-C15)/C15 -> 0.027486523 | E16: [fill] | F16: =IFERROR((D16-E16)*10000,0) -> 0 | G16: =(C16-100000000)/100000000 -> 0.0369768 | H16: =IFERROR((1+H15)*(1+E16)-1,0) -> 0
A17: 8 | B17: 8/14/2026 | C17: ='Portfolio Overview'!B20 -> 105174120 | D17: =(C17-C16)/C16 -> 0.014237927 | E17: [fill] | F17: =IFERROR((D17-E17)*10000,0) -> 0 | G17: =(C17-100000000)/100000000 -> 0.0517412 | H17: =IFERROR((1+H16)*(1+E17)-1,0) -> 0
A18: 9 | B18: 8/21/2026 | C18: ='Portfolio Overview'!B21 -> 103154120 | D18: =(C18-C17)/C17 -> -0.019206246 | E18: [fill] | F18: =IFERROR((D18-E18)*10000,0) -> 0 | G18: =(C18-100000000)/100000000 -> 0.0315412 | H18: =IFERROR((1+H17)*(1+E18)-1,0) -> 0
A19: 10 | B19: 8/28/2026 | C19: ='Portfolio Overview'!B22 -> 102910110 | D19: =(C19-C18)/C18 -> -0.0023654896 | E19: [fill] | F19: =IFERROR((D19-E19)*10000,0) -> 0 | G19: =(C19-100000000)/100000000 -> 0.0291011 | H19: =IFERROR((1+H18)*(1+E19)-1,0) -> 0
A21: SHARPE RATIO & INFORMATION RATIO (25% each of grade)
B22: Sharpe Ratio | C22: =IFERROR(((AVERAGE(D10:D19)-4%/52)*52)/(STDEV(D10:D19)*SQRT(52)),0) -> 0.9734984 | D22: Target: >0.5 good, >1.0 excellent
B23: Information Ratio | C23: =IFERROR((AVERAGE(F10:F19)*52)/(STDEV(F10:F19)*SQRT(52)),0) -> 0 | D23: Target: >0.5 good, >1.0 excellent
B24: Hit Rate | C24: =IFERROR(COUNTIF(F10:F19,">0")/10,0) -> 0 | D24: % weeks beating benchmark
B25: Cumulative Return | C25: =(C19-100000000)/100000000 -> 0.0291011 | D25: Total since inception
B26: vs SPY (fill in) | C26: [fill SPY %] | D26: Pull from Yahoo Finance

Sheet Bond Analysis
A1: FIXED INCOME SLEEVE ANALYSIS — PRE-TRADE RATIONALE & POST-TRADE TRACKING
A3: BOND SELECTION SCREEN — ALTERNATIVES CONSIDERED
A4: ETF | B4: Duration (yrs) | C4: Yield | D4: Decision | E4: Key Reason
A5: TLT | B5: ~20yr | C5: 4.80% | D5: ❌ REJECTED | E5: Too much duration risk — +200bps shock = -40% loss
A6: BND | B6: ~6.5yr | C6: 4.50% | D6: ❌ REJECTED | E6: Duration too high for hawkish Fed thesis
A7: AGG | B7: ~6.2yr | C7: 4.45% | D7: ❌ REJECTED | E7: Same issue as BND
A8: HYG | B8: ~4yr | C8: 7.20% | D8: ❌ REJECTED | E8: Too much credit risk, spreads near cycle tights
A9: VGIT | B9: 5.2yr | C9: 4.30% | D9: ✅ SELECTED | E9: Core Treasury carry, moderate duration, rate plateau
A10: VTIP | B10: 2.6yr | C10: 2.1% real | D10: ✅ SELECTED | E10: PCE 4.1% >> 2.5% breakeven — market underpricing inflation
A11: JPIE | B11: 3.8yr | C11: 5.80% | D11: ✅ SELECTED | E11: 142bps spread pickup, active mgmt, short duration
A12: MINT | B12: 0.35yr | C12: 4.40% | D12: ✅ SELECTED | E12: Near-zero rate risk, captures Fed funds rate, liquidity buffer
A15: BOND SLEEVE — POST-TRADE THESIS TRACKER
A16: Indicator | B16: At Purchase (Jun 28) | C16: Latest (Aug 28) | D16: Direction | E16: Thesis Holding?
A17: Fed Funds Rate | B17: 3.50–3.75% (Warsh hawkish) | C17: 3.50–3.75% (on hold) | D17: → Unchanged | E17: ✅ Yes — rates stayed high
A18: 10Y UST Yield | B18: ~4.40% | C18: 4.72% (+32bps) | D18: ↑ Higher | E18: ✅ Yes — validates short duration
A19: PCE Inflation | B19: 4.1% | C19: ~3.8% (sticky) | D19: → Elevated | E19: ✅ Yes — VTIP thesis intact
A20: Breakeven Inflation | B20: ~2.5% | C20: ~2.5% | D20: → Unchanged | E20: ✅ Yes — gap to PCE still 130bps+
A21: IG Credit Spread | B21: ~130bps | C21: ~142bps | D21: ↑ Wider | E21: ✅ Yes — JPIE spread still compensates
A22: VGIT Price Impact | B22: — | C22: -1.57% (-$157K) | D22: ↓ Down | E22: ✅ Expected — rate rise caused drop
A23: MINT performance | B23: — | C23: 0.00% (flat) | D23: → Stable | E23: ✅ Yes — near-zero duration worked
A24: Short duration thesis | B24: Hypothesis | C24: Confirmed | D24: ✓ Validated | E24: ✅ vs TLT which fell ~6.4%

Sheet Benchmark Calc
A1: BENCHMARK RETURN CALCULATOR — 60% VT + 40% VGIT
A3: Benchmark = 60% MSCI World + 40% Bloomberg Global Agg | Proxy: 60% VT + 40% VGIT | Fill VT and VGIT weekly returns from Yahoo Finance each Friday → copy col E to Weekly Performance tab col E
A5: # | B5: Friday | C5: VT Return | D5: VGIT Return | E5: Benchmark (60/40) | F5: → Copy to Weekly Perf col E
A6: 1 | B6: 6/26/2026 | C6: [fill %] | D6: [fill %] | E6: =IFERROR(0.6*C6+0.4*D6,0) -> 0 | F6: → Copy to 'Weekly Performance'!E10
A7: 2 | B7: 7/3/2026 | C7: [fill %] | D7: [fill %] | E7: =IFERROR(0.6*C7+0.4*D7,0) -> 0 | F7: → Copy to 'Weekly Performance'!E11
A8: 3 | B8: 7/10/2026 | C8: [fill %] | D8: [fill %] | E8: =IFERROR(0.6*C8+0.4*D8,0) -> 0 | F8: → Copy to 'Weekly Performance'!E12
A9: 4 | B9: 7/17/2026 | C9: [fill %] | D9: [fill %] | E9: =IFERROR(0.6*C9+0.4*D9,0) -> 0 | F9: → Copy to 'Weekly Performance'!E13
A10: 5 | B10: 7/24/2026 | C10: [fill %] | D10: [fill %] | E10: =IFERROR(0.6*C10+0.4*D10,0) -> 0 | F10: → Copy to 'Weekly Performance'!E14
A11: 6 | B11: 7/31/2026 | C11: [fill %] | D11: [fill %] | E11: =IFERROR(0.6*C11+0.4*D11,0) -> 0 | F11: → Copy to 'Weekly Performance'!E15
A12: 7 | B12: 8/7/2026 | C12: [fill %] | D12: [fill %] | E12: =IFERROR(0.6*C12+0.4*D12,0) -> 0 | F12: → Copy to 'Weekly Performance'!E16
A13: 8 | B13: 8/14/2026 | C13: [fill %] | D13: [fill %] | E13: =IFERROR(0.6*C13+0.4*D13,0) -> 0 | F13: → Copy to 'Weekly Performance'!E17
A14: 9 | B14: 8/21/2026 | C14: [fill %] | D14: [fill %] | E14: =IFERROR(0.6*C14+0.4*D14,0) -> 0 | F14: → Copy to 'Weekly Performance'!E18
A15: 10 | B15: 8/28/2026 | C15: [fill %] | D15: [fill %] | E15: =IFERROR(0.6*C15+0.4*D15,0) -> 0 | F15: → Copy to 'Weekly Performance'!E19

Sheet CAT Removal Log
A1: CAT REMOVAL LOG — CHANGES vs GPP2026_Complete_Analysis.xlsx (original, 30 Aug 2026)
A3: WHAT CHANGED
A4: Position PL Tracker | B4: CAT row deleted (was 4.0% weight, -$818,000 / -20.35% at 8/28). TOTAL row is now SUM / SUMPRODUCT formulas instead of typed numbers. Weight total added in C20.
A5: Position PL Tracker | B5: SPY weight set to 14.0% (original file had 10%). The live SharePoint copy shows 14.0%, and SPY's P/L % column only reconciles with a $14M cost basis.
A6: Attribution Analysis | B6: CAT row deleted. Every bps cell is now a formula: weight × P/L % × 10,000 from the tracker. Equity / Fixed Income / Portfolio totals are SUMs. Best and Worst contributor are INDEX/MATCH on P/L %.
A7: Portfolio Overview | B7: Weekly Portfolio Value = original StockTrak value minus CAT's P/L that week (see table below). Current Value, total return, Top Contributor and Largest Detractor are formulas.
A8: Weekly Performance | B8: Portfolio Value column now links to Portfolio Overview, so Sharpe, cumulative return etc. follow the ex-CAT values.
A9: Bond Analysis / Benchmark Calc | B9: Unchanged.
A10: ASSUMPTION | B10: If CAT had never been bought, its $4M would have sat in cash earning nothing, so each week's portfolio value falls by exactly CAT's cumulative P/L on that Friday. Cash interest on the $4M is ignored.
A12: WEEKLY RECONCILIATION — ORIGINAL vs ex-CAT
A13: Friday | B13: Original Portfolio Value ($) | C13: CAT P/L ($) | D13: ex-CAT Portfolio Value ($) | E13: Original Position P/L ($) | F13: ex-CAT Position P/L ($) | G13: Original Attribution (bps) | H13: ex-CAT Attribution (bps)
A14: 6/26/2026 | B14: 1.0044591e+08 | C14: 0 | D14: =B14-C14 -> 1.0044591e+08 | E14: 63465.16 | F14: ='Position PL Tracker'!D20 -> 63465.16 | G14: 39.7 | H14: ='Attribution Analysis'!B23 -> 35.485
A15: 7/3/2026 | B15: 1.0057154e+08 | C15: -164880 | D15: =B15-C15 -> 1.0073642e+08 | E15: -1802978.6 | F15: ='Position PL Tracker'!F20 -> -1638098.6 | G15: -175.6 | H15: ='Attribution Analysis'!C23 -> -156.86
A16: 7/10/2026 | B16: 100451369 | C16: -319840 | D16: =B16-C16 -> 100771209 | E16: -2239297.5 | F16: ='Position PL Tracker'!H20 -> -1919457.5 | G16: -213.8 | H16: ='Attribution Analysis'!D23 -> -179.38
A17: 7/17/2026 | B17: 97586405 | C17: -504400 | D17: =B17-C17 -> 98090805 | E17: -2253436.3 | F17: ='Position PL Tracker'!J20 -> -1749036.3 | G17: -213.8 | H17: ='Attribution Analysis'!E23 -> -160.03
A18: 7/24/2026 | B18: 98500000 | C18: -478520 | D18: =B18-C18 -> 98978520 | E18: 117680.47 | F18: ='Position PL Tracker'!L20 -> 596200.47 | G18: 8.1 | H18: ='Attribution Analysis'!F23 -> 67.7
A19: 7/31/2026 | B19: 100450000 | C19: -473640 | D19: =B19-C19 -> 100923640 | E19: 719011.09 | F19: ='Position PL Tracker'!N20 -> 1192651.1 | G19: 63.9 | H19: ='Attribution Analysis'!G23 -> 124.92
A20: 8/7/2026 | B20: 103100000 | C20: -597680 | D20: =B20-C20 -> 103697680 | E20: 1255075 | F20: ='Position PL Tracker'!P20 -> 1852755 | G20: 114.6 | H20: ='Attribution Analysis'!H23 -> 187.81
A21: 8/14/2026 | B21: 104600000 | C21: -574120 | D21: =B21-C21 -> 105174120 | E21: 2071751.3 | F21: ='Position PL Tracker'!R20 -> 2645871.3 | G21: 191.5 | H21: ='Attribution Analysis'!I23 -> 265.815
A22: 8/21/2026 | B22: 102540000 | C22: -614120 | D22: =B22-C22 -> 103154120 | E22: 1260527 | F22: ='Position PL Tracker'!T20 -> 1874647 | G22: 118.7 | H22: ='Attribution Analysis'!J23 -> 190.36
A23: 8/28/2026 | B23: 102092110 | C23: -818000 | D23: =B23-C23 -> 102910110 | E23: 1232921.3 | F23: ='Position PL Tracker'!V20 -> 2050921.3 | G23: 110.1 | H23: ='Attribution Analysis'!K23 -> 209.18
A25: Blue = typed from the original workbook (inputs). Green = links to the ex-CAT sheets. Black = formulas. CAT was not held on 6/26, so its P/L that week is $0.
